s3same/__init__.py
s3same/iam.py
s3same/travis.py
s3same-0.1.data/scripts/s3same
s3same-0.1.dist-info/DESCRIPTION.rst
s3same-0.1.dist-info/METADATA
s3same-0.1.dist-info/RECORD
s3same-0.1.dist-info/WHEEL
s3same-0.1.dist-info/metadata.json
s3same-0.1.dist-info/top_level.txt
