Metadata-Version: 2.0
Name: s3same
Version: 0.1
Summary: Configure Travis-CI artifact uploading to S3
Home-page: http://github.com/vokal/s3same
Author: Vokal
Author-email: pypi@vokal.io
License: MIT
Keywords: travis ci s3 artifact
Platform: UNKNOWN
Classifier: Development Status :: 2 - Pre-Alpha
Classifier: License :: OSI Approved :: MIT License
Classifier: Programming Language :: Python :: 2.7
Classifier: Programming Language :: Python :: 3
Requires-Dist: boto3
Requires-Dist: click
Requires-Dist: pycrypto
Requires-Dist: python-dotenv
Requires-Dist: pyyaml
Requires-Dist: travispy
